README.md
pyproject.toml
setup.cfg
setup.py
iparapheur_internal/__init__.py
iparapheur_internal/api_client.py
iparapheur_internal/api_response.py
iparapheur_internal/configuration.py
iparapheur_internal/exceptions.py
iparapheur_internal/py.typed
iparapheur_internal/rest.py
iparapheur_internal.egg-info/PKG-INFO
iparapheur_internal.egg-info/SOURCES.txt
iparapheur_internal.egg-info/dependency_links.txt
iparapheur_internal.egg-info/requires.txt
iparapheur_internal.egg-info/top_level.txt
iparapheur_internal/api/__init__.py
iparapheur_internal/api/admin_advanced_config_api.py
iparapheur_internal/api/admin_all_users_api.py
iparapheur_internal/api/admin_desk_api.py
iparapheur_internal/api/admin_external_signature_api.py
iparapheur_internal/api/admin_folder_api.py
iparapheur_internal/api/admin_layer_api.py
iparapheur_internal/api/admin_seal_certificate_api.py
iparapheur_internal/api/admin_secure_mail_api.py
iparapheur_internal/api/admin_template_api.py
iparapheur_internal/api/admin_trash_bin_api.py
iparapheur_internal/api/admin_typology_api.py
iparapheur_internal/api/admin_workflow_definition_api.py
iparapheur_internal/api/current_user_api.py
iparapheur_internal/api/desk_api.py
iparapheur_internal/api/document_api.py
iparapheur_internal/api/folder_api.py
iparapheur_internal/api/secure_mail_api.py
iparapheur_internal/api/server_info_api.py
iparapheur_internal/api/template_api.py
iparapheur_internal/api/tenant_api.py
iparapheur_internal/api/typology_api.py
iparapheur_internal/api/workflow_api.py
iparapheur_internal/models/__init__.py
iparapheur_internal/models/action.py
iparapheur_internal/models/columned_task_list_request.py
iparapheur_internal/models/composite_id.py
iparapheur_internal/models/create_file_stamp_request.py
iparapheur_internal/models/create_folder_request.py
iparapheur_internal/models/delegation_dto.py
iparapheur_internal/models/delegation_sort_by.py
iparapheur_internal/models/desk_representation.py
iparapheur_internal/models/detached_signature.py
iparapheur_internal/models/detached_signature_dto.py
iparapheur_internal/models/document_dto.py
iparapheur_internal/models/document_type.py
iparapheur_internal/models/error_response.py
