Metadata-Version: 2.4
Name: iparapheur_internal
Version: 1.19.10
Summary: iparapheur
Home-page: 
Author: Libriciel SCOP
Author-email: Libriciel SCOP <iparapheur@libriciel.coop>
License-Expression: MIT
Project-URL: Repository, https://github.com/GIT_USER_ID/GIT_REPO_ID
Keywords: OpenAPI,OpenAPI-Generator,iparapheur
Requires-Python: >=3.9
Requires-Dist: urllib3<3.0.0,>=2.1.0
Requires-Dist: python-dateutil>=2.8.2
Requires-Dist: pydantic>=2
Requires-Dist: typing-extensions>=4.7.1
Requires-Dist: lazy-imports<2,>=1
Dynamic: author
